{
  "title": "Celeste 5B (rooms)",
  "attempt_count": 0,
  "splits": [
    {
      "title": "-1",
      "time": "0.000000",
      "best_time": "0.000000",
      "best_segment": "0.000000"
    },
    {
      "title": "-2",
      "time": "0.000000",
      "best_time": "0.000000",
      "best_segment": "0.000000"
    },
    {
      "title": "-3",
      "time": "0.000000",
      "best_time": "0.000000",
      "best_segment": "0.000000"
    },
    {
      "title": "{Start} 4",
      "time": "0.000000",
      "best_time": "0.000000",
      "best_segment": "0.000000"
    },
    {
      "title": "-5",
      "time": "0.000000",
      "best_time": "0.000000",
      "best_segment": "0.000000"
    },
    {
      "title": "-6 (Bubs)",
      "time": "0.000000",
      "best_time": "0.000000",
      "best_segment": "0.000000"
    },
    {
      "title": "-7",
      "time": "0.000000",
      "best_time": "0.000000",
      "best_segment": "0.000000"
    },
    {
      "title": "-8",
      "time": "0.000000",
      "best_time": "0.000000",
      "best_segment": "0.000000"
    },
    {
      "title": "-9 (Spike jump)",
      "time": "0.000000",
      "best_time": "0.000000",
      "best_segment": "0.000000"
    },
    {
      "title": "{Central Chamber}10",
      "time": "0.000000",
      "best_time": "0.000000",
      "best_segment": "0.000000"
    },
    {
      "title": "-11",
      "time": "0.000000",
      "best_time": "0.000000",
      "best_segment": "0.000000"
    },
    {
      "title": "-12",
      "time": "0.000000",
      "best_time": "0.000000",
      "best_segment": "0.000000"
    },
    {
      "title": "-13",
      "time": "0.000000",
      "best_time": "0.000000",
      "best_segment": "0.000000"
    },
    {
      "title": "-14",
      "time": "0.000000",
      "best_time": "0.000000",
      "best_segment": "0.000000"
    },
    {
      "title": "{Through the Mirror}15",
      "time": "0.000000",
      "best_time": "0.000000",
      "best_segment": "0.000000"
    },
    {
      "title": "-16",
      "time": "0.000000",
      "best_time": "0.000000",
      "best_segment": "0.000000"
    },
    {
      "title": "-17",
      "time": "0.000000",
      "best_time": "0.000000",
      "best_segment": "0.000000"
    },
    {
      "title": "-18 (Gauntlet)",
      "time": "0.000000",
      "best_time": "0.000000",
      "best_segment": "0.000000"
    },
    {
      "title": "-19",
      "time": "0.000000",
      "best_time": "0.000000",
      "best_segment": "0.000000"
    },
    {
      "title": "-20",
      "time": "0.000000",
      "best_time": "0.000000",
      "best_segment": "0.000000"
    },
    {
      "title": "{Mix Master} Heart",
      "time": "0.000000",
      "best_time": "0.000000",
      "best_segment": "0.000000"
    }
  ],
  "width": 60,
  "height": 80
}